llama_notifications/__init__.py
llama_notifications/config.py
llama_notifications/context.py
llama_notifications/core.py
llama_notifications/package.py
llama_notifications/priority.py
llama_notifications/security.py
llama_notifications/spam_filter.py
llama_notifications-0.1.0.dist-info/METADATA
llama_notifications-0.1.0.dist-info/WHEEL
llama_notifications-0.1.0.dist-info/licenses/LICENSE
llama_notifications-0.1.0.dist-info/RECORD
