Metadata-Version: 2.4
Name: llama-notifications
Version: 0.1.0
Summary: Notification system for the LlamaAI Ecosystem (push, email, SMS).
Project-URL: Homepage, https://github.com/llama-ai/llama-notifications
Author-email: Llama Notifications Team <team@llamanotifications.dev>
License: MIT
License-File: LICENSE
Keywords: alerting,email,llama,notifications,push,sms
Classifier: Development Status :: 3 - Alpha
Classifier: Intended Audience :: Developers
Classifier: License :: OSI Approved :: MIT License
Classifier: Programming Language :: Python :: 3
Requires-Python: >=3.8
Requires-Dist: apns2>=0.5.0
Requires-Dist: cryptography>=41.0.7
Requires-Dist: firebase-admin>=6.2.0
Requires-Dist: hyper>=0.7.0
Requires-Dist: pydantic>=2.4.2
Requires-Dist: pyjwt>=2.8.0
Requires-Dist: python-dotenv>=1.0.0
Requires-Dist: requests>=2.31.0
Requires-Dist: sendgrid>=6.10.0
Requires-Dist: twilio>=8.5.0
Provides-Extra: dev
Requires-Dist: bandit>=1.7.5; extra == 'dev'
Requires-Dist: black>=23.9.1; extra == 'dev'
Requires-Dist: build>=1.0.3; extra == 'dev'
Requires-Dist: coverage>=7.3.2; extra == 'dev'
Requires-Dist: flake8>=6.1.0; extra == 'dev'
Requires-Dist: isort>=5.12.0; extra == 'dev'
Requires-Dist: mypy>=1.5.1; extra == 'dev'
Requires-Dist: pre-commit>=3.4.0; extra == 'dev'
Requires-Dist: pytest-asyncio>=0.21.1; extra == 'dev'
Requires-Dist: pytest-cov>=4.1.0; extra == 'dev'
Requires-Dist: pytest-mock>=3.11.1; extra == 'dev'
Requires-Dist: pytest>=7.4.2; extra == 'dev'
Requires-Dist: safety>=2.3.5; extra == 'dev'
Requires-Dist: sphinx-autodoc-typehints>=1.24.0; extra == 'dev'
Requires-Dist: sphinx-rtd-theme>=1.3.0; extra == 'dev'
Requires-Dist: sphinx>=7.2.6; extra == 'dev'
Requires-Dist: twine>=4.0.2; extra == 'dev'
Requires-Dist: types-pyjwt>=1.7.1; extra == 'dev'
Requires-Dist: types-requests>=2.31.0.2; extra == 'dev'
Provides-Extra: mlx
Requires-Dist: mlx>=0.0.17; extra == 'mlx'
